pyseleniumbot/__init__.py
pyseleniumbot/api_crud/__init__.py
pyseleniumbot/api_crud/crud.py
pyseleniumbot/mobile/__init__.py
pyseleniumbot/mobile/mobAppium.py
pyseleniumbot/mobile/pollWait.py
pyseleniumbot/mobile/session.py
pyseleniumbot/web/DropDown.py
pyseleniumbot/web/__init__.py
pyseleniumbot/web/alerts.py
pyseleniumbot/web/dragAndDrop.py
pyseleniumbot/web/webElement.py
pyseleniumbot/web/webWaits.py
pyseleniumbot/web/windowAndFrame.py
pyseleniumbot-1.0.14.dist-info/LICENSE
pyseleniumbot-1.0.14.dist-info/METADATA
pyseleniumbot-1.0.14.dist-info/WHEEL
pyseleniumbot-1.0.14.dist-info/top_level.txt
pyseleniumbot-1.0.14.dist-info/RECORD
